tree_sitter_toml/__init__.py
tree_sitter_toml/__init__.pyi
tree_sitter_toml/_binding.pyd
tree_sitter_toml/binding.c
tree_sitter_toml/py.typed
tree_sitter_toml/queries/highlights.scm
tree_sitter_toml-0.7.0.dist-info/LICENSE
tree_sitter_toml-0.7.0.dist-info/METADATA
tree_sitter_toml-0.7.0.dist-info/WHEEL
tree_sitter_toml-0.7.0.dist-info/top_level.txt
tree_sitter_toml-0.7.0.dist-info/RECORD
