Metadata-Version: 2.1
Name: tree-sitter-toml
Version: 0.7.0
Summary: TOML grammar for tree-sitter
Author-email: Ika <ikatyang@gmail.com>
License: MIT
Project-URL: Homepage, https://github.com/tree-sitter-grammars/tree-sitter-toml
Keywords: incremental,parsing,tree-sitter,toml
Classifier: Intended Audience :: Developers
Classifier: Topic :: Software Development :: Compilers
Classifier: Topic :: Text Processing :: Linguistic
Classifier: Typing :: Typed
Requires-Python: >=3.9
License-File: LICENSE
Provides-Extra: core
Requires-Dist: tree-sitter~=0.22; extra == "core"
